sharh/__init__.py
sharh/expr.py
sharh/parser.py
sharh/parsetab.py
sharh-0.9.0.dist-info/LICENSE
sharh-0.9.0.dist-info/METADATA
sharh-0.9.0.dist-info/WHEEL
sharh-0.9.0.dist-info/top_level.txt
sharh-0.9.0.dist-info/RECORD
